{"updated_at": "2026-06-24 16:28:06", "market_status": "NXT_EVE", "fx": {"USDKRW": 1545.0, "EURKRW": 1753.0}, "stocks": [{"code": "005930", "name": "삼성전자", "krx_live": 338500.0, "krx_live_chg": 9.19, "krx_close": 340500.0, "binance": {"symbol": "SAMSUNGUSDT", "price": 219.33, "ccy": "USDT", "chg_pct": 4.64, "krw": 338865, "prem_live": 0.11, "prem_close": -0.48}, "gdr": {"ticker": "SMSN.IL", "tv": "LSIN:SMSN", "ccy": "USD", "price": 5475.0, "ratio": 25, "chg_pct": -2.23, "ts": 1782285150, "krw": 338355, "prem_live": -0.04, "prem_close": -0.63}}, {"code": "000660", "name": "SK하이닉스", "krx_live": 2587000.0, "krx_live_chg": 1.25, "krx_close": 2621000.0, "binance": {"symbol": "SKHYNIXUSDT", "price": 1685.02, "ccy": "USDT", "chg_pct": -2.25, "krw": 2603356, "prem_live": 0.63, "prem_close": -0.67}, "gdr": {"ticker": "HY9H.F", "tv": "FWB:HY9H", "ccy": "EUR", "price": 1475.0, "ratio": 1, "chg_pct": -7.23, "ts": 1782285069, "krw": 2585675, "prem_live": -0.05, "prem_close": -1.35}}]}