{"updated_at": "2026-06-26 16:49:04", "market_status": "NXT_EVE", "fx": {"USDKRW": 1538.6, "EURKRW": 1750.8}, "stocks": [{"code": "005930", "name": "삼성전자", "krx_live": 341000.0, "krx_live_chg": -4.88, "krx_close": 339500.0, "binance": {"symbol": "SAMSUNGUSDT", "price": 221.42, "ccy": "USDT", "chg_pct": -4.55, "krw": 340677, "prem_live": -0.09, "prem_close": 0.35}, "gdr": {"ticker": "SMSN.IL", "tv": "LSIN:SMSN", "ccy": "USD", "price": 5545.0, "ratio": 25, "chg_pct": -2.89, "ts": 1782459208, "krw": 341261, "prem_live": 0.08, "prem_close": 0.52}}, {"code": "000660", "name": "SK하이닉스", "krx_live": 2714000.0, "krx_live_chg": -6.96, "krx_close": 2673000.0, "binance": {"symbol": "SKHYNIXUSDT", "price": 1754.51, "ccy": "USDT", "chg_pct": -7.73, "krw": 2699489, "prem_live": -0.53, "prem_close": 0.99}, "gdr": {"ticker": "HY9H.F", "tv": "FWB:HY9H", "ccy": "EUR", "price": 1560.0, "ratio": 1, "chg_pct": -8.24, "ts": 1782459050, "krw": 2731248, "prem_live": 0.64, "prem_close": 2.18}}]}