{"updated_at": "2026-06-24 15:50:05", "market_status": "NXT_EVE", "fx": {"USDKRW": 1544.6, "EURKRW": 1755.0}, "stocks": [{"code": "005930", "name": "삼성전자", "krx_live": 340000.0, "krx_live_chg": 9.68, "krx_close": 340500.0, "binance": {"symbol": "SAMSUNGUSDT", "price": 219.73, "ccy": "USDT", "chg_pct": 7.23, "krw": 339395, "prem_live": -0.18, "prem_close": -0.32}, "gdr": {"ticker": "SMSN.IL", "tv": "LSIN:SMSN", "ccy": "USD", "price": 5075.0, "ratio": 25, "chg_pct": -6.37, "ts": 1782229110, "krw": 313554, "prem_live": -7.78, "prem_close": -7.91}}, {"code": "000660", "name": "SK하이닉스", "krx_live": 2589000.0, "krx_live_chg": 1.33, "krx_close": 2621000.0, "binance": {"symbol": "SKHYNIXUSDT", "price": 1688.75, "ccy": "USDT", "chg_pct": -0.42, "krw": 2608443, "prem_live": 0.75, "prem_close": -0.48}, "gdr": {"ticker": "HY9H.F", "tv": "FWB:HY9H", "ccy": "EUR", "price": 1495.0, "ratio": 1, "chg_pct": -5.97, "ts": 1782282848, "krw": 2623725, "prem_live": 1.34, "prem_close": 0.1}}]}