{"updated_at": "2026-06-22 16:45:05", "market_status": "NXT_EVE", "fx": {"USDKRW": 1541.3, "EURKRW": 1763.3}, "stocks": [{"code": "005930", "name": "삼성전자", "krx_live": 354500.0, "krx_live_chg": 0.14, "krx_close": 352500.0, "binance": {"symbol": "SAMSUNGUSDT", "price": 229.81, "ccy": "USDT", "chg_pct": -5.67, "krw": 354206, "prem_live": -0.08, "prem_close": 0.48}, "gdr": {"ticker": "SMSN.IL", "tv": "LSIN:SMSN", "ccy": "USD", "price": 5710.0, "ratio": 25, "chg_pct": 0.71, "ts": 1782113343, "krw": 352033, "prem_live": -0.7, "prem_close": -0.13}}, {"code": "000660", "name": "SK하이닉스", "krx_live": 2926000.0, "krx_live_chg": 5.86, "krx_close": 2918000.0, "binance": {"symbol": "SKHYNIXUSDT", "price": 1897.83, "ccy": "USDT", "chg_pct": -1.9, "krw": 2925125, "prem_live": -0.03, "prem_close": 0.24}, "gdr": {"ticker": "HY9H.F", "tv": "FWB:HY9H", "ccy": "EUR", "price": 1670.0, "ratio": 1, "chg_pct": 28.46, "ts": 1782113398, "krw": 2944711, "prem_live": 0.64, "prem_close": 0.92}}]}