{"updated_at": "2026-06-30 00:53:05", "market_status": "K200F_NIGHT", "fx": {"USDKRW": 1542.4, "EURKRW": 1760.1}, "stocks": [{"code": "005930", "name": "삼성전자", "krx_live": 324000.0, "krx_live_chg": -4.57, "krx_close": 326000.0, "binance": {"symbol": "SAMSUNGUSDT", "price": 208.1, "ccy": "USDT", "chg_pct": -8.44, "krw": 320973, "prem_live": -0.93, "prem_close": -1.54}, "gdr": {"ticker": "SMSN.IL", "tv": "LSIN:SMSN", "ccy": "USD", "price": 5115.0, "ratio": 25, "chg_pct": -11.96, "ts": 1782747316, "krw": 315575, "prem_live": -2.6, "prem_close": -3.2}}, {"code": "000660", "name": "SK하이닉스", "krx_live": 2616000.0, "krx_live_chg": -2.13, "krx_close": 2628000.0, "binance": {"symbol": "SKHYNIXUSDT", "price": 1677.12, "ccy": "USDT", "chg_pct": -7.28, "krw": 2586790, "prem_live": -1.12, "prem_close": -1.57}, "gdr": {"ticker": "HY9H.F", "tv": "FWB:HY9H", "ccy": "EUR", "price": 1445.0, "ratio": 1, "chg_pct": -2.36, "ts": 1782747470, "krw": 2543344, "prem_live": -2.78, "prem_close": -3.22}}]}