{"updated_at": "2026-06-30 01:14:04", "market_status": "K200F_NIGHT", "fx": {"USDKRW": 1542.8, "EURKRW": 1761.7}, "stocks": [{"code": "005930", "name": "삼성전자", "krx_live": 324000.0, "krx_live_chg": -4.57, "krx_close": 326000.0, "binance": {"symbol": "SAMSUNGUSDT", "price": 207.7, "ccy": "USDT", "chg_pct": -8.7, "krw": 320440, "prem_live": -1.1, "prem_close": -1.71}, "gdr": {"ticker": "SMSN.IL", "tv": "LSIN:SMSN", "ccy": "USD", "price": 5115.0, "ratio": 25, "chg_pct": -11.96, "ts": 1782747316, "krw": 315657, "prem_live": -2.58, "prem_close": -3.17}}, {"code": "000660", "name": "SK하이닉스", "krx_live": 2616000.0, "krx_live_chg": -2.13, "krx_close": 2628000.0, "binance": {"symbol": "SKHYNIXUSDT", "price": 1687.34, "ccy": "USDT", "chg_pct": -6.89, "krw": 2603228, "prem_live": -0.49, "prem_close": -0.94}, "gdr": {"ticker": "HY9H.F", "tv": "FWB:HY9H", "ccy": "EUR", "price": 1460.0, "ratio": 1, "chg_pct": -1.35, "ts": 1782748566, "krw": 2572082, "prem_live": -1.68, "prem_close": -2.13}}]}