{
  "trd_ymd": "20260605",
  "market": "KOSPI",
  "rows": [
    {
      "ITM_CD": "105560",
      "ITM_NM": "KB금융",
      "SCTR_NM": "은행",
      "EPRC": 170600,
      "UD_RT": 3.9,
      "HPRC": 175700,
      "W52_HPRC": 175700,
      "W52_LPRC": 105300,
      "TRD_AMT": null
    },
    {
      "ITM_CD": "055550",
      "ITM_NM": "신한지주",
      "SCTR_NM": "은행",
      "EPRC": 107200,
      "UD_RT": 7.09,
      "HPRC": 109800,
      "W52_HPRC": 109800,
      "W52_LPRC": 58100,
      "TRD_AMT": null
    },
    {
      "ITM_CD": "004170",
      "ITM_NM": "신세계",
      "SCTR_NM": "백화점과일반상점",
      "EPRC": 637000,
      "UD_RT": -3.34,
      "HPRC": 722000,
      "W52_HPRC": 722000,
      "W52_LPRC": 160800,
      "TRD_AMT": null
    },
    {
      "ITM_CD": "023530",
      "ITM_NM": "롯데쇼핑",
      "SCTR_NM": "백화점과일반상점",
      "EPRC": 174000,
      "UD_RT": 1.16,
      "HPRC": 180200,
      "W52_HPRC": 180200,
      "W52_LPRC": 62700,
      "TRD_AMT": null
    },
    {
      "ITM_CD": "069960",
      "ITM_NM": "현대백화점",
      "SCTR_NM": "백화점과일반상점",
      "EPRC": 147500,
      "UD_RT": 5.51,
      "HPRC": 155900,
      "W52_HPRC": 155900,
      "W52_LPRC": 67900,
      "TRD_AMT": null
    },
    {
      "ITM_CD": "085620",
      "ITM_NM": "미래에셋생명",
      "SCTR_NM": "생명보험",
      "EPRC": 18740,
      "UD_RT": -3.45,
      "HPRC": 24200,
      "W52_HPRC": 24200,
      "W52_LPRC": 5630,
      "TRD_AMT": null
    }
  ]
}