{
  "updated_at": "2026-06-24 19:16:51",
  "indicators": {
    "SOX": {
      "name": "필라델피아 반도체",
      "val": 13482.5098,
      "prev": 14634.723,
      "chg_amt": -1152.2132,
      "chg_rt": -7.87
    },
    "TNX": {
      "name": "10Y 국채금리",
      "val": 4.493,
      "prev": 4.509,
      "chg_amt": -0.016,
      "chg_rt": -0.35
    },
    "DXY": {
      "name": "달러인덱스",
      "val": 101.648,
      "prev": 101.458,
      "chg_amt": 0.19,
      "chg_rt": 0.19
    },
    "VIX": {
      "name": "VIX",
      "val": 19.29,
      "prev": 19.48,
      "chg_amt": -0.19,
      "chg_rt": -0.98
    },
    "WTI": {
      "name": "WTI 원유",
      "val": 72.09,
      "prev": 73.21,
      "chg_amt": -1.12,
      "chg_rt": -1.53
    },
    "RUT": {
      "name": "러셀2000",
      "val": 2975.48,
      "prev": 3004.4036,
      "chg_amt": -28.9236,
      "chg_rt": -0.96
    },
    "YM_F": {
      "name": "다우 선물",
      "val": 51993.0,
      "prev": 52082.0,
      "chg_amt": -89.0,
      "chg_rt": -0.17
    },
    "NQ_F": {
      "name": "나스닥 선물",
      "val": 29792.0,
      "prev": 29666.0,
      "chg_amt": 126.0,
      "chg_rt": 0.42
    },
    "ES_F": {
      "name": "S&P 500 선물",
      "val": 7445.5,
      "prev": 7437.5,
      "chg_amt": 8.0,
      "chg_rt": 0.11
    }
  }
}